{
  "date": "2026-06-28",
  "node_name": "节点A",
  "storage_name": "示例储能电站",
  "summary": {
    "total_energy_revenue": -31233.03,
    "total_agc_capacity_revenue": 8198.55,
    "total_agc_mileage_revenue": 6475.56,
    "total_gross_revenue": -16558.92,
    "total_deviation_penalty": 11575.51,
    "total_transmission_fee": 6.81,
    "total_gov_fund_fee": 4.27,
    "total_ancillary_fee": 73.39,
    "agc_unqualified_count": 0,
    "agc_unqualified_penalty": 0.0,
    "total_market_cost": 11659.98,
    "total_battery_degradation": 0.0,
    "total_self_consumption": 0.0,
    "total_om_cost": 0.0,
    "total_operating_cost": 0.0,
    "total_cost": 11659.98,
    "net_profit": -28218.9,
    "kp": 1.072,
    "total_charge_mwh": 189.2,
    "total_discharge_mwh": 37.1,
    "final_soc": 0.8763
  },
  "intervals": [
    {
      "time": "00:00",
      "soc": 0.2314,
      "net_power_mw": 0.0,
      "lmp": 256.31,
      "energy_revenue": 0.0,
      "agc_capacity_revenue": 87.14,
      "agc_mileage_revenue": 0.0,
      "deviation_penalty": 0.0,
      "transmission_fee": 0.0,
      "gov_fund_fee": 0.0,
      "ancillary_fee": 0.44,
      "battery_degradation_cost": 0.0,
      "self_consumption_cost": 0.0,
      "net_revenue": 86.7
    },
    {
      "time": "00:15",
      "soc": 0.2312,
      "net_power_mw": 0.0,
      "lmp": 244.07,
      "energy_revenue": 0.0,
      "agc_capacity_revenue": 90.51,
      "agc_mileage_revenue": 0.0,
      "deviation_penalty": 0.0,
      "transmission_fee": 0.0,
      "gov_fund_fee": 0.0,
      "ancillary_fee": 0.45,
      "battery_degradation_cost": 0.0,
      "self_consumption_cost": 0.0,
      "net_revenue": 90.06
    },
    {
      "time": "00:30",
      "soc": 0.2309,
      "net_power_mw": 0.0,
      "lmp": 252.24,
      "energy_revenue": 0.0,
      "agc_capacity_revenue": 77.03,
      "agc_mileage_revenue": 0.0,
      "deviation_penalty": 0.0,
      "transmission_fee": 0.0,
      "gov_fund_fee": 0.0,
      "ancillary_fee": 0.39,
      "battery_degradation_cost": 0.0,
      "self_consumption_cost": 0.0,
      "net_revenue": 76.64
    },
    {
      "time": "00:45",
      "soc": 0.2307,
      "net_power_mw": 0.0,
      "lmp": 248.57,
      "energy_revenue": 0.0,
      "agc_capacity_revenue": 82.85,
      "agc_mileage_revenue": 0.0,
      "deviation_penalty": 0.0,
      "transmission_fee": 0.0,
      "gov_fund_fee": 0.0,
      "ancillary_fee": 0.41,
      "battery_degradation_cost": 0.0,
      "self_consumption_cost": 0.0,
      "net_revenue": 82.44
    },
    {
      "time": "01:00",
      "soc": 0.2304,
      "net_power_mw": 0.0,
      "lmp": 242.17,
      "energy_revenue": 0.0,
      "agc_capacity_revenue": 70.45,
      "agc_mileage_revenue": 0.0,
      "deviation_penalty": 0.0,
      "transmission_fee": 0.0,
      "gov_fund_fee": 0.0,
      "ancillary_fee": 0.35,
      "battery_degradation_cost": 0.0,
      "self_consumption_cost": 0.0,
      "net_revenue": 70.1
    },
    {
      "time": "01:15",
      "soc": 0.2302,
      "net_power_mw": 0.0,
      "lmp": 237.91,
      "energy_revenue": 0.0,
      "agc_capacity_revenue": 78.1,
      "agc_mileage_revenue": 0.0,
      "deviation_penalty": 0.0,
      "transmission_fee": 0.0,
      "gov_fund_fee": 0.0,
      "ancillary_fee": 0.39,
      "battery_degradation_cost": 0.0,
      "self_consumption_cost": 0.0,
      "net_revenue": 77.71
    },
    {
      "time": "01:30",
      "soc": 0.2299,
      "net_power_mw": 0.0,
      "lmp": 229.84,
      "energy_revenue": 0.0,
      "agc_capacity_revenue": 85.22,
      "agc_mileage_revenue": 0.0,
      "deviation_penalty": 0.0,
      "transmission_fee": 0.0,
      "gov_fund_fee": 0.0,
      "ancillary_fee": 0.43,
      "battery_degradation_cost": 0.0,
      "self_consumption_cost": 0.0,
      "net_revenue": 84.79
    },
    {
      "time": "01:45",
      "soc": 0.2297,
      "net_power_mw": 0.0,
      "lmp": 224.74,
      "energy_revenue": 0.0,
      "agc_capacity_revenue": 90.2,
      "agc_mileage_revenue": 0.0,
      "deviation_penalty": 0.0,
      "transmission_fee": 0.0,
      "gov_fund_fee": 0.0,
      "ancillary_fee": 0.45,
      "battery_degradation_cost": 0.0,
      "self_consumption_cost": 0.0,
      "net_revenue": 89.75
    },
    {
      "time": "02:00",
      "soc": 0.3075,
      "net_power_mw": -67.83,
      "lmp": 221.03,
      "energy_revenue": -3747.9,
      "agc_capacity_revenue": 85.15,
      "agc_mileage_revenue": 0.0,
      "deviation_penalty": 0.0,
      "transmission_fee": 0.51,
      "gov_fund_fee": 0.32,
      "ancillary_fee": 0.43,
      "battery_degradation_cost": 0.0,
      "self_consumption_cost": 0.0,
      "net_revenue": -3664.01
    },
    {
      "time": "02:15",
      "soc": 0.3072,
      "net_power_mw": 0.0,
      "lmp": 226.12,
      "energy_revenue": 0.0,
      "agc_capacity_revenue": 84.08,
      "agc_mileage_revenue": 0.0,
      "deviation_penalty": 0.0,
      "transmission_fee": 0.0,
      "gov_fund_fee": 0.0,
      "ancillary_fee": 0.42,
      "battery_degradation_cost": 0.0,
      "self_consumption_cost": 0.0,
      "net_revenue": 83.66
    },
    {
      "time": "02:30",
      "soc": 0.385,
      "net_power_mw": -67.83,
      "lmp": 213.77,
      "energy_revenue": -3624.79,
      "agc_capacity_revenue": 81.85,
      "agc_mileage_revenue": 0.0,
      "deviation_penalty": 0.0,
      "transmission_fee": 0.51,
      "gov_fund_fee": 0.32,
      "ancillary_fee": 0.41,
      "battery_degradation_cost": 0.0,
      "self_consumption_cost": 0.0,
      "net_revenue": -3544.18
    },
    {
      "time": "02:45",
      "soc": 0.4627,
      "net_power_mw": -67.83,
      "lmp": 216.71,
      "energy_revenue": -3674.64,
      "agc_capacity_revenue": 79.56,
      "agc_mileage_revenue": 0.0,
      "deviation_penalty": 0.0,
      "transmission_fee": 0.51,
      "gov_fund_fee": 0.32,
      "ancillary_fee": 0.4,
      "battery_degradation_cost": 0.0,
      "self_consumption_cost": 0.0,
      "net_revenue": -3596.31
    },
    {
      "time": "03:00",
      "soc": 0.5405,
      "net_power_mw": -67.83,
      "lmp": 225.56,
      "energy_revenue": -3824.71,
      "agc_capacity_revenue": 69.76,
      "agc_mileage_revenue": 0.0,
      "deviation_penalty": 0.0,
      "transmission_fee": 0.51,
      "gov_fund_fee": 0.32,
      "ancillary_fee": 0.35,
      "battery_degradation_cost": 0.0,
      "self_consumption_cost": 0.0,
      "net_revenue": -3756.13
    },
    {
      "time": "03:15",
      "soc": 0.5602,
      "net_power_mw": -17.39,
      "lmp": 223.38,
      "energy_revenue": -971.21,
      "agc_capacity_revenue": 61.95,
      "agc_mileage_revenue": 0.0,
      "deviation_penalty": 6.51,
      "transmission_fee": 0.13,
      "gov_fund_fee": 0.08,
      "ancillary_fee": 0.31,
      "battery_degradation_cost": 0.0,
      "self_consumption_cost": 0.0,
      "net_revenue": -916.29
    },
    {
      "time": "03:30",
      "soc": 0.638,
      "net_power_mw": -67.83,
      "lmp": 219.37,
      "energy_revenue": -3719.75,
      "agc_capacity_revenue": 67.15,
      "agc_mileage_revenue": 0.0,
      "deviation_penalty": 0.0,
      "transmission_fee": 0.51,
      "gov_fund_fee": 0.32,
      "ancillary_fee": 0.34,
      "battery_degradation_cost": 0.0,
      "self_consumption_cost": 0.0,
      "net_revenue": -3653.77
    },
    {
      "time": "03:45",
      "soc": 0.7157,
      "net_power_mw": -67.83,
      "lmp": 218.24,
      "energy_revenue": -3700.59,
      "agc_capacity_revenue": 67.46,
      "agc_mileage_revenue": 0.0,
      "deviation_penalty": 0.0,
      "transmission_fee": 0.51,
      "gov_fund_fee": 0.32,
      "ancillary_fee": 0.34,
      "battery_degradation_cost": 0.0,
      "self_consumption_cost": 0.0,
      "net_revenue": -3634.3
    },
    {
      "time": "04:00",
      "soc": 0.7231,
      "net_power_mw": -6.67,
      "lmp": 239.22,
      "energy_revenue": -398.9,
      "agc_capacity_revenue": 83.16,
      "agc_mileage_revenue": 368.25,
      "deviation_penalty": 39.89,
      "transmission_fee": 0.05,
      "gov_fund_fee": 0.03,
      "ancillary_fee": 2.26,
      "battery_degradation_cost": 0.0,
      "self_consumption_cost": 0.0,
      "net_revenue": 10.28
    },
    {
      "time": "04:15",
      "soc": 0.7989,
      "net_power_mw": -66.09,
      "lmp": 223.88,
      "energy_revenue": -3698.9,
      "agc_capacity_revenue": 85.3,
      "agc_mileage_revenue": 0.0,
      "deviation_penalty": 0.0,
      "transmission_fee": 0.5,
      "gov_fund_fee": 0.31,
      "ancillary_fee": 0.43,
      "battery_degradation_cost": 0.0,
      "self_consumption_cost": 0.0,
      "net_revenue": -3614.84
    },
    {
      "time": "04:30",
      "soc": 0.7868,
      "net_power_mw": 8.73,
      "lmp": 239.06,
      "energy_revenue": 521.75,
      "agc_capacity_revenue": 83.69,
      "agc_mileage_revenue": 481.98,
      "deviation_penalty": 52.17,
      "transmission_fee": 0.07,
      "gov_fund_fee": 0.04,
      "ancillary_fee": 2.83,
      "battery_degradation_cost": 0.0,
      "self_consumption_cost": 0.0,
      "net_revenue": 1032.31
    },
    {
      "time": "04:45",
      "soc": 0.7865,
      "net_power_mw": 0.0,
      "lmp": 251.68,
      "energy_revenue": 0.0,
      "agc_capacity_revenue": 79.1,
      "agc_mileage_revenue": 0.0,
      "deviation_penalty": 0.0,
      "transmission_fee": 0.0,
      "gov_fund_fee": 0.0,
      "ancillary_fee": 0.4,
      "battery_degradation_cost": 0.0,
      "self_consumption_cost": 0.0,
      "net_revenue": 78.7
    },
    {
      "time": "05:00",
      "soc": 0.7863,
      "net_power_mw": 0.0,
      "lmp": 235.63,
      "energy_revenue": 0.0,
      "agc_capacity_revenue": 89.82,
      "agc_mileage_revenue": 0.0,
      "deviation_penalty": 0.0,
      "transmission_fee": 0.0,
      "gov_fund_fee": 0.0,
      "ancillary_fee": 0.45,
      "battery_degradation_cost": 0.0,
      "self_consumption_cost": 0.0,
      "net_revenue": 89.37
    },
    {
      "time": "05:15",
      "soc": 0.786,
      "net_power_mw": 0.0,
      "lmp": 259.48,
      "energy_revenue": 0.0,
      "agc_capacity_revenue": 89.97,
      "agc_mileage_revenue": 0.0,
      "deviation_penalty": 0.0,
      "transmission_fee": 0.0,
      "gov_fund_fee": 0.0,
      "ancillary_fee": 0.45,
      "battery_degradation_cost": 0.0,
      "self_consumption_cost": 0.0,
      "net_revenue": 89.52
    },
    {
      "time": "05:30",
      "soc": 0.7858,
      "net_power_mw": 0.0,
      "lmp": 262.76,
      "energy_revenue": 0.0,
      "agc_capacity_revenue": 81.24,
      "agc_mileage_revenue": 0.0,
      "deviation_penalty": 0.0,
      "transmission_fee": 0.0,
      "gov_fund_fee": 0.0,
      "ancillary_fee": 0.41,
      "battery_degradation_cost": 0.0,
      "self_consumption_cost": 0.0,
      "net_revenue": 80.83
    },
    {
      "time": "05:45",
      "soc": 0.7855,
      "net_power_mw": 0.0,
      "lmp": 274.57,
      "energy_revenue": 0.0,
      "agc_capacity_revenue": 72.82,
      "agc_mileage_revenue": 0.0,
      "deviation_penalty": 0.0,
      "transmission_fee": 0.0,
      "gov_fund_fee": 0.0,
      "ancillary_fee": 0.36,
      "battery_degradation_cost": 0.0,
      "self_consumption_cost": 0.0,
      "net_revenue": 72.46
    },
    {
      "time": "06:00",
      "soc": 0.7853,
      "net_power_mw": 0.0,
      "lmp": 283.24,
      "energy_revenue": 0.0,
      "agc_capacity_revenue": 96.33,
      "agc_mileage_revenue": 0.0,
      "deviation_penalty": 0.0,
      "transmission_fee": 0.0,
      "gov_fund_fee": 0.0,
      "ancillary_fee": 0.48,
      "battery_degradation_cost": 0.0,
      "self_consumption_cost": 0.0,
      "net_revenue": 95.85
    },
    {
      "time": "06:15",
      "soc": 0.785,
      "net_power_mw": 0.0,
      "lmp": 309.03,
      "energy_revenue": 0.0,
      "agc_capacity_revenue": 101.23,
      "agc_mileage_revenue": 0.0,
      "deviation_penalty": 0.0,
      "transmission_fee": 0.0,
      "gov_fund_fee": 0.0,
      "ancillary_fee": 0.51,
      "battery_degradation_cost": 0.0,
      "self_consumption_cost": 0.0,
      "net_revenue": 100.72
    },
    {
      "time": "06:30",
      "soc": 0.7848,
      "net_power_mw": 0.0,
      "lmp": 326.25,
      "energy_revenue": 0.0,
      "agc_capacity_revenue": 94.72,
      "agc_mileage_revenue": 0.0,
      "deviation_penalty": 0.0,
      "transmission_fee": 0.0,
      "gov_fund_fee": 0.0,
      "ancillary_fee": 0.47,
      "battery_degradation_cost": 0.0,
      "self_consumption_cost": 0.0,
      "net_revenue": 94.25
    },
    {
      "time": "06:45",
      "soc": 0.7845,
      "net_power_mw": 0.0,
      "lmp": 347.7,
      "energy_revenue": 0.0,
      "agc_capacity_revenue": 94.49,
      "agc_mileage_revenue": 0.0,
      "deviation_penalty": 0.0,
      "transmission_fee": 0.0,
      "gov_fund_fee": 0.0,
      "ancillary_fee": 0.47,
      "battery_degradation_cost": 0.0,
      "self_consumption_cost": 0.0,
      "net_revenue": 94.02
    },
    {
      "time": "07:00",
      "soc": 0.7843,
      "net_power_mw": 0.0,
      "lmp": 374.67,
      "energy_revenue": 0.0,
      "agc_capacity_revenue": 95.56,
      "agc_mileage_revenue": 0.0,
      "deviation_penalty": 0.0,
      "transmission_fee": 0.0,
      "gov_fund_fee": 0.0,
      "ancillary_fee": 0.48,
      "battery_degradation_cost": 0.0,
      "self_consumption_cost": 0.0,
      "net_revenue": 95.08
    },
    {
      "time": "07:15",
      "soc": 0.784,
      "net_power_mw": 0.0,
      "lmp": 376.77,
      "energy_revenue": 0.0,
      "agc_capacity_revenue": 100.84,
      "agc_mileage_revenue": 0.0,
      "deviation_penalty": 0.0,
      "transmission_fee": 0.0,
      "gov_fund_fee": 0.0,
      "ancillary_fee": 0.5,
      "battery_degradation_cost": 0.0,
      "self_consumption_cost": 0.0,
      "net_revenue": 100.34
    },
    {
      "time": "07:30",
      "soc": 0.7838,
      "net_power_mw": 0.0,
      "lmp": 390.18,
      "energy_revenue": 0.0,
      "agc_capacity_revenue": 102.68,
      "agc_mileage_revenue": 0.0,
      "deviation_penalty": 0.0,
      "transmission_fee": 0.0,
      "gov_fund_fee": 0.0,
      "ancillary_fee": 0.51,
      "battery_degradation_cost": 0.0,
      "self_consumption_cost": 0.0,
      "net_revenue": 102.17
    },
    {
      "time": "07:45",
      "soc": 0.6935,
      "net_power_mw": 66.24,
      "lmp": 427.87,
      "energy_revenue": 7085.53,
      "agc_capacity_revenue": 101.38,
      "agc_mileage_revenue": 0.0,
      "deviation_penalty": 0.0,
      "transmission_fee": 0.5,
      "gov_fund_fee": 0.31,
      "ancillary_fee": 0.51,
      "battery_degradation_cost": 0.0,
      "self_consumption_cost": 0.0,
      "net_revenue": 7185.59
    },
    {
      "time": "08:00",
      "soc": 0.6013,
      "net_power_mw": 67.71,
      "lmp": 425.61,
      "energy_revenue": 7204.73,
      "agc_capacity_revenue": 85.38,
      "agc_mileage_revenue": 0.0,
      "deviation_penalty": 0.0,
      "transmission_fee": 0.51,
      "gov_fund_fee": 0.32,
      "ancillary_fee": 0.43,
      "battery_degradation_cost": 0.0,
      "self_consumption_cost": 0.0,
      "net_revenue": 7288.85
    },
    {
      "time": "08:15",
      "soc": 0.601,
      "net_power_mw": 0.0,
      "lmp": 433.54,
      "energy_revenue": 0.0,
      "agc_capacity_revenue": 87.6,
      "agc_mileage_revenue": 0.0,
      "deviation_penalty": 711.88,
      "transmission_fee": 0.0,
      "gov_fund_fee": 0.0,
      "ancillary_fee": 0.44,
      "battery_degradation_cost": 0.0,
      "self_consumption_cost": 0.0,
      "net_revenue": -624.72
    },
    {
      "time": "08:30",
      "soc": 0.6097,
      "net_power_mw": -7.79,
      "lmp": 443.23,
      "energy_revenue": -863.19,
      "agc_capacity_revenue": 78.49,
      "agc_mileage_revenue": 430.09,
      "deviation_penalty": 829.93,
      "transmission_fee": 0.06,
      "gov_fund_fee": 0.04,
      "ancillary_fee": 2.54,
      "battery_degradation_cost": 0.0,
      "self_consumption_cost": 0.0,
      "net_revenue": -1187.18
    },
    {
      "time": "08:45",
      "soc": 0.6062,
      "net_power_mw": 2.44,
      "lmp": 438.67,
      "energy_revenue": 267.59,
      "agc_capacity_revenue": 73.59,
      "agc_mileage_revenue": 134.71,
      "deviation_penalty": 709.2,
      "transmission_fee": 0.02,
      "gov_fund_fee": 0.01,
      "ancillary_fee": 1.04,
      "battery_degradation_cost": 0.0,
      "self_consumption_cost": 0.0,
      "net_revenue": -234.38
    },
    {
      "time": "09:00",
      "soc": 0.6059,
      "net_power_mw": 0.0,
      "lmp": 433.42,
      "energy_revenue": 0.0,
      "agc_capacity_revenue": 79.4,
      "agc_mileage_revenue": 0.0,
      "deviation_penalty": 711.68,
      "transmission_fee": 0.0,
      "gov_fund_fee": 0.0,
      "ancillary_fee": 0.4,
      "battery_degradation_cost": 0.0,
      "self_consumption_cost": 0.0,
      "net_revenue": -632.68
    },
    {
      "time": "09:15",
      "soc": 0.6127,
      "net_power_mw": -6.15,
      "lmp": 424.7,
      "energy_revenue": -652.98,
      "agc_capacity_revenue": 101.0,
      "agc_mileage_revenue": 339.54,
      "deviation_penalty": 383.66,
      "transmission_fee": 0.05,
      "gov_fund_fee": 0.03,
      "ancillary_fee": 2.2,
      "battery_degradation_cost": 0.0,
      "self_consumption_cost": 0.0,
      "net_revenue": -598.38
    },
    {
      "time": "09:30",
      "soc": 0.6174,
      "net_power_mw": -4.28,
      "lmp": 409.64,
      "energy_revenue": -438.31,
      "agc_capacity_revenue": 95.41,
      "agc_mileage_revenue": 236.3,
      "deviation_penalty": 43.83,
      "transmission_fee": 0.03,
      "gov_fund_fee": 0.02,
      "ancillary_fee": 1.66,
      "battery_degradation_cost": 0.0,
      "self_consumption_cost": 0.0,
      "net_revenue": -152.14
    },
    {
      "time": "09:45",
      "soc": 0.6171,
      "net_power_mw": 0.0,
      "lmp": 386.25,
      "energy_revenue": 0.0,
      "agc_capacity_revenue": 102.61,
      "agc_mileage_revenue": 0.0,
      "deviation_penalty": 0.0,
      "transmission_fee": 0.0,
      "gov_fund_fee": 0.0,
      "ancillary_fee": 0.51,
      "battery_degradation_cost": 0.0,
      "self_consumption_cost": 0.0,
      "net_revenue": 102.1
    },
    {
      "time": "10:00",
      "soc": 0.6169,
      "net_power_mw": 0.0,
      "lmp": 373.7,
      "energy_revenue": 0.0,
      "agc_capacity_revenue": 93.11,
      "agc_mileage_revenue": 0.0,
      "deviation_penalty": 0.0,
      "transmission_fee": 0.0,
      "gov_fund_fee": 0.0,
      "ancillary_fee": 0.47,
      "battery_degradation_cost": 0.0,
      "self_consumption_cost": 0.0,
      "net_revenue": 92.64
    },
    {
      "time": "10:15",
      "soc": 0.6166,
      "net_power_mw": 0.0,
      "lmp": 340.37,
      "energy_revenue": 0.0,
      "agc_capacity_revenue": 74.96,
      "agc_mileage_revenue": 0.0,
      "deviation_penalty": 0.0,
      "transmission_fee": 0.0,
      "gov_fund_fee": 0.0,
      "ancillary_fee": 0.37,
      "battery_degradation_cost": 0.0,
      "self_consumption_cost": 0.0,
      "net_revenue": 74.59
    },
    {
      "time": "10:30",
      "soc": 0.6164,
      "net_power_mw": 0.0,
      "lmp": 336.36,
      "energy_revenue": 0.0,
      "agc_capacity_revenue": 91.27,
      "agc_mileage_revenue": 0.0,
      "deviation_penalty": 0.0,
      "transmission_fee": 0.0,
      "gov_fund_fee": 0.0,
      "ancillary_fee": 0.46,
      "battery_degradation_cost": 0.0,
      "self_consumption_cost": 0.0,
      "net_revenue": 90.81
    },
    {
      "time": "10:45",
      "soc": 0.6161,
      "net_power_mw": 0.0,
      "lmp": 317.02,
      "energy_revenue": 0.0,
      "agc_capacity_revenue": 82.47,
      "agc_mileage_revenue": 0.0,
      "deviation_penalty": 0.0,
      "transmission_fee": 0.0,
      "gov_fund_fee": 0.0,
      "ancillary_fee": 0.41,
      "battery_degradation_cost": 0.0,
      "self_consumption_cost": 0.0,
      "net_revenue": 82.06
    },
    {
      "time": "11:00",
      "soc": 0.6139,
      "net_power_mw": 1.45,
      "lmp": 289.55,
      "energy_revenue": 104.96,
      "agc_capacity_revenue": 80.63,
      "agc_mileage_revenue": 80.05,
      "deviation_penalty": 10.5,
      "transmission_fee": 0.01,
      "gov_fund_fee": 0.01,
      "ancillary_fee": 0.8,
      "battery_degradation_cost": 0.0,
      "self_consumption_cost": 0.0,
      "net_revenue": 254.32
    },
    {
      "time": "11:15",
      "soc": 0.6137,
      "net_power_mw": 0.0,
      "lmp": 279.04,
      "energy_revenue": 0.0,
      "agc_capacity_revenue": 83.23,
      "agc_mileage_revenue": 0.0,
      "deviation_penalty": 0.0,
      "transmission_fee": 0.0,
      "gov_fund_fee": 0.0,
      "ancillary_fee": 0.42,
      "battery_degradation_cost": 0.0,
      "self_consumption_cost": 0.0,
      "net_revenue": 82.81
    },
    {
      "time": "11:30",
      "soc": 0.6134,
      "net_power_mw": 0.0,
      "lmp": 261.53,
      "energy_revenue": 0.0,
      "agc_capacity_revenue": 92.96,
      "agc_mileage_revenue": 0.0,
      "deviation_penalty": 0.0,
      "transmission_fee": 0.0,
      "gov_fund_fee": 0.0,
      "ancillary_fee": 0.46,
      "battery_degradation_cost": 0.0,
      "self_consumption_cost": 0.0,
      "net_revenue": 92.5
    },
    {
      "time": "11:45",
      "soc": 0.6132,
      "net_power_mw": 0.0,
      "lmp": 258.78,
      "energy_revenue": 0.0,
      "agc_capacity_revenue": 80.94,
      "agc_mileage_revenue": 0.0,
      "deviation_penalty": 425.64,
      "transmission_fee": 0.0,
      "gov_fund_fee": 0.0,
      "ancillary_fee": 0.4,
      "battery_degradation_cost": 0.0,
      "self_consumption_cost": 0.0,
      "net_revenue": -345.1
    },
    {
      "time": "12:00",
      "soc": 0.6909,
      "net_power_mw": -67.83,
      "lmp": 248.46,
      "energy_revenue": -4213.01,
      "agc_capacity_revenue": 72.9,
      "agc_mileage_revenue": 0.0,
      "deviation_penalty": 0.0,
      "transmission_fee": 0.51,
      "gov_fund_fee": 0.32,
      "ancillary_fee": 0.36,
      "battery_degradation_cost": 0.0,
      "self_consumption_cost": 0.0,
      "net_revenue": -4141.3
    },
    {
      "time": "12:15",
      "soc": 0.6907,
      "net_power_mw": 0.0,
      "lmp": 251.25,
      "energy_revenue": 0.0,
      "agc_capacity_revenue": 67.15,
      "agc_mileage_revenue": 0.0,
      "deviation_penalty": 413.25,
      "transmission_fee": 0.0,
      "gov_fund_fee": 0.0,
      "ancillary_fee": 0.34,
      "battery_degradation_cost": 0.0,
      "self_consumption_cost": 0.0,
      "net_revenue": -346.44
    },
    {
      "time": "12:30",
      "soc": 0.7224,
      "net_power_mw": -27.83,
      "lmp": 251.2,
      "energy_revenue": -1747.47,
      "agc_capacity_revenue": 77.26,
      "agc_mileage_revenue": 0.0,
      "deviation_penalty": 238.42,
      "transmission_fee": 0.21,
      "gov_fund_fee": 0.13,
      "ancillary_fee": 0.39,
      "battery_degradation_cost": 0.0,
      "self_consumption_cost": 0.0,
      "net_revenue": -1909.36
    },
    {
      "time": "12:45",
      "soc": 0.8002,
      "net_power_mw": -67.83,
      "lmp": 237.36,
      "energy_revenue": -4024.79,
      "agc_capacity_revenue": 64.47,
      "agc_mileage_revenue": 0.0,
      "deviation_penalty": 0.0,
      "transmission_fee": 0.51,
      "gov_fund_fee": 0.32,
      "ancillary_fee": 0.32,
      "battery_degradation_cost": 0.0,
      "self_consumption_cost": 0.0,
      "net_revenue": -3961.47
    },
    {
      "time": "13:00",
      "soc": 0.7999,
      "net_power_mw": 0.0,
      "lmp": 253.6,
      "energy_revenue": 0.0,
      "agc_capacity_revenue": 77.26,
      "agc_mileage_revenue": 0.0,
      "deviation_penalty": 417.12,
      "transmission_fee": 0.0,
      "gov_fund_fee": 0.0,
      "ancillary_fee": 0.39,
      "battery_degradation_cost": 0.0,
      "self_consumption_cost": 0.0,
      "net_revenue": -340.25
    },
    {
      "time": "13:15",
      "soc": 0.7997,
      "net_power_mw": 0.0,
      "lmp": 253.69,
      "energy_revenue": 0.0,
      "agc_capacity_revenue": 70.14,
      "agc_mileage_revenue": 0.0,
      "deviation_penalty": 417.26,
      "transmission_fee": 0.0,
      "gov_fund_fee": 0.0,
      "ancillary_fee": 0.35,
      "battery_degradation_cost": 0.0,
      "self_consumption_cost": 0.0,
      "net_revenue": -347.47
    },
    {
      "time": "13:30",
      "soc": 0.7994,
      "net_power_mw": 0.0,
      "lmp": 266.28,
      "energy_revenue": 0.0,
      "agc_capacity_revenue": 73.74,
      "agc_mileage_revenue": 0.0,
      "deviation_penalty": 0.0,
      "transmission_fee": 0.0,
      "gov_fund_fee": 0.0,
      "ancillary_fee": 0.37,
      "battery_degradation_cost": 0.0,
      "self_consumption_cost": 0.0,
      "net_revenue": 73.37
    },
    {
      "time": "13:45",
      "soc": 0.7992,
      "net_power_mw": 0.0,
      "lmp": 270.28,
      "energy_revenue": 0.0,
      "agc_capacity_revenue": 80.02,
      "agc_mileage_revenue": 0.0,
      "deviation_penalty": 0.0,
      "transmission_fee": 0.0,
      "gov_fund_fee": 0.0,
      "ancillary_fee": 0.4,
      "battery_degradation_cost": 0.0,
      "self_consumption_cost": 0.0,
      "net_revenue": 79.62
    },
    {
      "time": "14:00",
      "soc": 0.7989,
      "net_power_mw": 0.0,
      "lmp": 258.15,
      "energy_revenue": 0.0,
      "agc_capacity_revenue": 79.02,
      "agc_mileage_revenue": 0.0,
      "deviation_penalty": 283.07,
      "transmission_fee": 0.0,
      "gov_fund_fee": 0.0,
      "ancillary_fee": 0.4,
      "battery_degradation_cost": 0.0,
      "self_consumption_cost": 0.0,
      "net_revenue": -204.45
    },
    {
      "time": "14:15",
      "soc": 0.7987,
      "net_power_mw": 0.0,
      "lmp": 262.34,
      "energy_revenue": 0.0,
      "agc_capacity_revenue": 87.14,
      "agc_mileage_revenue": 0.0,
      "deviation_penalty": 0.0,
      "transmission_fee": 0.0,
      "gov_fund_fee": 0.0,
      "ancillary_fee": 0.44,
      "battery_degradation_cost": 0.0,
      "self_consumption_cost": 0.0,
      "net_revenue": 86.7
    },
    {
      "time": "14:30",
      "soc": 0.7984,
      "net_power_mw": 0.0,
      "lmp": 270.77,
      "energy_revenue": 0.0,
      "agc_capacity_revenue": 80.71,
      "agc_mileage_revenue": 0.0,
      "deviation_penalty": 0.0,
      "transmission_fee": 0.0,
      "gov_fund_fee": 0.0,
      "ancillary_fee": 0.4,
      "battery_degradation_cost": 0.0,
      "self_consumption_cost": 0.0,
      "net_revenue": 80.31
    },
    {
      "time": "14:45",
      "soc": 0.8061,
      "net_power_mw": -6.85,
      "lmp": 278.74,
      "energy_revenue": -477.34,
      "agc_capacity_revenue": 83.31,
      "agc_mileage_revenue": 378.19,
      "deviation_penalty": 47.73,
      "transmission_fee": 0.05,
      "gov_fund_fee": 0.03,
      "ancillary_fee": 2.31,
      "battery_degradation_cost": 0.0,
      "self_consumption_cost": 0.0,
      "net_revenue": -65.96
    },
    {
      "time": "15:00",
      "soc": 0.8058,
      "net_power_mw": 0.0,
      "lmp": 287.17,
      "energy_revenue": 0.0,
      "agc_capacity_revenue": 87.98,
      "agc_mileage_revenue": 0.0,
      "deviation_penalty": 0.0,
      "transmission_fee": 0.0,
      "gov_fund_fee": 0.0,
      "ancillary_fee": 0.44,
      "battery_degradation_cost": 0.0,
      "self_consumption_cost": 0.0,
      "net_revenue": 87.54
    },
    {
      "time": "15:15",
      "soc": 0.8056,
      "net_power_mw": 0.0,
      "lmp": 283.59,
      "energy_revenue": 0.0,
      "agc_capacity_revenue": 77.26,
      "agc_mileage_revenue": 0.0,
      "deviation_penalty": 0.0,
      "transmission_fee": 0.0,
      "gov_fund_fee": 0.0,
      "ancillary_fee": 0.39,
      "battery_degradation_cost": 0.0,
      "self_consumption_cost": 0.0,
      "net_revenue": 76.87
    },
    {
      "time": "15:30",
      "soc": 0.8053,
      "net_power_mw": 0.0,
      "lmp": 303.61,
      "energy_revenue": 0.0,
      "agc_capacity_revenue": 85.91,
      "agc_mileage_revenue": 0.0,
      "deviation_penalty": 0.0,
      "transmission_fee": 0.0,
      "gov_fund_fee": 0.0,
      "ancillary_fee": 0.43,
      "battery_degradation_cost": 0.0,
      "self_consumption_cost": 0.0,
      "net_revenue": 85.48
    },
    {
      "time": "15:45",
      "soc": 0.8051,
      "net_power_mw": 0.0,
      "lmp": 313.89,
      "energy_revenue": 0.0,
      "agc_capacity_revenue": 79.71,
      "agc_mileage_revenue": 0.0,
      "deviation_penalty": 0.0,
      "transmission_fee": 0.0,
      "gov_fund_fee": 0.0,
      "ancillary_fee": 0.4,
      "battery_degradation_cost": 0.0,
      "self_consumption_cost": 0.0,
      "net_revenue": 79.31
    },
    {
      "time": "16:00",
      "soc": 0.8048,
      "net_power_mw": 0.0,
      "lmp": 312.55,
      "energy_revenue": 0.0,
      "agc_capacity_revenue": 102.38,
      "agc_mileage_revenue": 0.0,
      "deviation_penalty": 0.0,
      "transmission_fee": 0.0,
      "gov_fund_fee": 0.0,
      "ancillary_fee": 0.51,
      "battery_degradation_cost": 0.0,
      "self_consumption_cost": 0.0,
      "net_revenue": 101.87
    },
    {
      "time": "16:15",
      "soc": 0.8046,
      "net_power_mw": 0.0,
      "lmp": 339.37,
      "energy_revenue": 0.0,
      "agc_capacity_revenue": 96.1,
      "agc_mileage_revenue": 0.0,
      "deviation_penalty": 0.0,
      "transmission_fee": 0.0,
      "gov_fund_fee": 0.0,
      "ancillary_fee": 0.48,
      "battery_degradation_cost": 0.0,
      "self_consumption_cost": 0.0,
      "net_revenue": 95.62
    },
    {
      "time": "16:30",
      "soc": 0.8137,
      "net_power_mw": -8.21,
      "lmp": 347.86,
      "energy_revenue": -713.98,
      "agc_capacity_revenue": 89.28,
      "agc_mileage_revenue": 453.27,
      "deviation_penalty": 71.4,
      "transmission_fee": 0.06,
      "gov_fund_fee": 0.04,
      "ancillary_fee": 2.71,
      "battery_degradation_cost": 0.0,
      "self_consumption_cost": 0.0,
      "net_revenue": -245.64
    },
    {
      "time": "16:45",
      "soc": 0.8135,
      "net_power_mw": 0.0,
      "lmp": 355.63,
      "energy_revenue": 0.0,
      "agc_capacity_revenue": 90.28,
      "agc_mileage_revenue": 0.0,
      "deviation_penalty": 0.0,
      "transmission_fee": 0.0,
      "gov_fund_fee": 0.0,
      "ancillary_fee": 0.45,
      "battery_degradation_cost": 0.0,
      "self_consumption_cost": 0.0,
      "net_revenue": 89.83
    },
    {
      "time": "17:00",
      "soc": 0.8257,
      "net_power_mw": -10.81,
      "lmp": 384.69,
      "energy_revenue": -1039.62,
      "agc_capacity_revenue": 103.14,
      "agc_mileage_revenue": 596.82,
      "deviation_penalty": 103.96,
      "transmission_fee": 0.08,
      "gov_fund_fee": 0.05,
      "ancillary_fee": 3.5,
      "battery_degradation_cost": 0.0,
      "self_consumption_cost": 0.0,
      "net_revenue": -447.25
    },
    {
      "time": "17:15",
      "soc": 0.8254,
      "net_power_mw": 0.0,
      "lmp": 395.14,
      "energy_revenue": 0.0,
      "agc_capacity_revenue": 96.79,
      "agc_mileage_revenue": 0.0,
      "deviation_penalty": 0.0,
      "transmission_fee": 0.0,
      "gov_fund_fee": 0.0,
      "ancillary_fee": 0.48,
      "battery_degradation_cost": 0.0,
      "self_consumption_cost": 0.0,
      "net_revenue": 96.31
    },
    {
      "time": "17:30",
      "soc": 0.8252,
      "net_power_mw": 0.0,
      "lmp": 417.18,
      "energy_revenue": 0.0,
      "agc_capacity_revenue": 89.21,
      "agc_mileage_revenue": 0.0,
      "deviation_penalty": 0.0,
      "transmission_fee": 0.0,
      "gov_fund_fee": 0.0,
      "ancillary_fee": 0.45,
      "battery_degradation_cost": 0.0,
      "self_consumption_cost": 0.0,
      "net_revenue": 88.76
    },
    {
      "time": "17:45",
      "soc": 0.8395,
      "net_power_mw": -12.68,
      "lmp": 429.3,
      "energy_revenue": -1360.88,
      "agc_capacity_revenue": 92.04,
      "agc_mileage_revenue": 700.06,
      "deviation_penalty": 136.09,
      "transmission_fee": 0.1,
      "gov_fund_fee": 0.06,
      "ancillary_fee": 3.96,
      "battery_degradation_cost": 0.0,
      "self_consumption_cost": 0.0,
      "net_revenue": -708.99
    },
    {
      "time": "18:00",
      "soc": 0.8393,
      "net_power_mw": 0.0,
      "lmp": 452.87,
      "energy_revenue": 0.0,
      "agc_capacity_revenue": 89.36,
      "agc_mileage_revenue": 0.0,
      "deviation_penalty": 0.0,
      "transmission_fee": 0.0,
      "gov_fund_fee": 0.0,
      "ancillary_fee": 0.45,
      "battery_degradation_cost": 0.0,
      "self_consumption_cost": 0.0,
      "net_revenue": 88.91
    },
    {
      "time": "18:15",
      "soc": 0.839,
      "net_power_mw": 0.0,
      "lmp": 461.6,
      "energy_revenue": 0.0,
      "agc_capacity_revenue": 87.37,
      "agc_mileage_revenue": 0.0,
      "deviation_penalty": 329.55,
      "transmission_fee": 0.0,
      "gov_fund_fee": 0.0,
      "ancillary_fee": 0.44,
      "battery_degradation_cost": 0.0,
      "self_consumption_cost": 0.0,
      "net_revenue": -242.62
    },
    {
      "time": "18:30",
      "soc": 0.8388,
      "net_power_mw": 0.0,
      "lmp": 462.26,
      "energy_revenue": 0.0,
      "agc_capacity_revenue": 93.11,
      "agc_mileage_revenue": 0.0,
      "deviation_penalty": 759.04,
      "transmission_fee": 0.0,
      "gov_fund_fee": 0.0,
      "ancillary_fee": 0.47,
      "battery_degradation_cost": 0.0,
      "self_consumption_cost": 0.0,
      "net_revenue": -666.4
    },
    {
      "time": "18:45",
      "soc": 0.8385,
      "net_power_mw": 0.0,
      "lmp": 483.22,
      "energy_revenue": 0.0,
      "agc_capacity_revenue": 86.99,
      "agc_mileage_revenue": 0.0,
      "deviation_penalty": 810.7,
      "transmission_fee": 0.0,
      "gov_fund_fee": 0.0,
      "ancillary_fee": 0.43,
      "battery_degradation_cost": 0.0,
      "self_consumption_cost": 0.0,
      "net_revenue": -724.14
    },
    {
      "time": "19:00",
      "soc": 0.8383,
      "net_power_mw": 0.0,
      "lmp": 478.36,
      "energy_revenue": 0.0,
      "agc_capacity_revenue": 87.52,
      "agc_mileage_revenue": 0.0,
      "deviation_penalty": 802.55,
      "transmission_fee": 0.0,
      "gov_fund_fee": 0.0,
      "ancillary_fee": 0.44,
      "battery_degradation_cost": 0.0,
      "self_consumption_cost": 0.0,
      "net_revenue": -715.47
    },
    {
      "time": "19:15",
      "soc": 0.8523,
      "net_power_mw": -12.44,
      "lmp": 484.05,
      "energy_revenue": -1505.4,
      "agc_capacity_revenue": 75.73,
      "agc_mileage_revenue": 686.81,
      "deviation_penalty": 962.64,
      "transmission_fee": 0.09,
      "gov_fund_fee": 0.06,
      "ancillary_fee": 3.81,
      "battery_degradation_cost": 0.0,
      "self_consumption_cost": 0.0,
      "net_revenue": -1709.46
    },
    {
      "time": "19:30",
      "soc": 0.8496,
      "net_power_mw": 1.83,
      "lmp": 470.87,
      "energy_revenue": 215.42,
      "agc_capacity_revenue": 89.21,
      "agc_mileage_revenue": 101.03,
      "deviation_penalty": 751.63,
      "transmission_fee": 0.01,
      "gov_fund_fee": 0.01,
      "ancillary_fee": 0.95,
      "battery_degradation_cost": 0.0,
      "self_consumption_cost": 0.0,
      "net_revenue": -346.94
    },
    {
      "time": "19:45",
      "soc": 0.8493,
      "net_power_mw": 0.0,
      "lmp": 464.17,
      "energy_revenue": 0.0,
      "agc_capacity_revenue": 83.92,
      "agc_mileage_revenue": 0.0,
      "deviation_penalty": 762.17,
      "transmission_fee": 0.0,
      "gov_fund_fee": 0.0,
      "ancillary_fee": 0.42,
      "battery_degradation_cost": 0.0,
      "self_consumption_cost": 0.0,
      "net_revenue": -678.67
    },
    {
      "time": "20:00",
      "soc": 0.8491,
      "net_power_mw": 0.0,
      "lmp": 443.09,
      "energy_revenue": 0.0,
      "agc_capacity_revenue": 96.02,
      "agc_mileage_revenue": 0.0,
      "deviation_penalty": 0.0,
      "transmission_fee": 0.0,
      "gov_fund_fee": 0.0,
      "ancillary_fee": 0.48,
      "battery_degradation_cost": 0.0,
      "self_consumption_cost": 0.0,
      "net_revenue": 95.54
    },
    {
      "time": "20:15",
      "soc": 0.8556,
      "net_power_mw": -5.92,
      "lmp": 428.13,
      "energy_revenue": -633.63,
      "agc_capacity_revenue": 98.09,
      "agc_mileage_revenue": 326.84,
      "deviation_penalty": 63.36,
      "transmission_fee": 0.04,
      "gov_fund_fee": 0.03,
      "ancillary_fee": 2.12,
      "battery_degradation_cost": 0.0,
      "self_consumption_cost": 0.0,
      "net_revenue": -274.25
    },
    {
      "time": "20:30",
      "soc": 0.8554,
      "net_power_mw": 0.0,
      "lmp": 419.15,
      "energy_revenue": 0.0,
      "agc_capacity_revenue": 99.54,
      "agc_mileage_revenue": 0.0,
      "deviation_penalty": 0.0,
      "transmission_fee": 0.0,
      "gov_fund_fee": 0.0,
      "ancillary_fee": 0.5,
      "battery_degradation_cost": 0.0,
      "self_consumption_cost": 0.0,
      "net_revenue": 99.04
    },
    {
      "time": "20:45",
      "soc": 0.8551,
      "net_power_mw": 0.0,
      "lmp": 386.18,
      "energy_revenue": 0.0,
      "agc_capacity_revenue": 105.59,
      "agc_mileage_revenue": 0.0,
      "deviation_penalty": 0.0,
      "transmission_fee": 0.0,
      "gov_fund_fee": 0.0,
      "ancillary_fee": 0.53,
      "battery_degradation_cost": 0.0,
      "self_consumption_cost": 0.0,
      "net_revenue": 105.06
    },
    {
      "time": "21:00",
      "soc": 0.8549,
      "net_power_mw": 0.0,
      "lmp": 377.45,
      "energy_revenue": 0.0,
      "agc_capacity_revenue": 89.13,
      "agc_mileage_revenue": 0.0,
      "deviation_penalty": 0.0,
      "transmission_fee": 0.0,
      "gov_fund_fee": 0.0,
      "ancillary_fee": 0.45,
      "battery_degradation_cost": 0.0,
      "self_consumption_cost": 0.0,
      "net_revenue": 88.68
    },
    {
      "time": "21:15",
      "soc": 0.8546,
      "net_power_mw": 0.0,
      "lmp": 366.38,
      "energy_revenue": 0.0,
      "agc_capacity_revenue": 84.92,
      "agc_mileage_revenue": 0.0,
      "deviation_penalty": 0.0,
      "transmission_fee": 0.0,
      "gov_fund_fee": 0.0,
      "ancillary_fee": 0.42,
      "battery_degradation_cost": 0.0,
      "self_consumption_cost": 0.0,
      "net_revenue": 84.5
    },
    {
      "time": "21:30",
      "soc": 0.8544,
      "net_power_mw": 0.0,
      "lmp": 351.85,
      "energy_revenue": 0.0,
      "agc_capacity_revenue": 80.86,
      "agc_mileage_revenue": 0.0,
      "deviation_penalty": 0.0,
      "transmission_fee": 0.0,
      "gov_fund_fee": 0.0,
      "ancillary_fee": 0.4,
      "battery_degradation_cost": 0.0,
      "self_consumption_cost": 0.0,
      "net_revenue": 80.46
    },
    {
      "time": "21:45",
      "soc": 0.8541,
      "net_power_mw": 0.0,
      "lmp": 335.33,
      "energy_revenue": 0.0,
      "agc_capacity_revenue": 88.06,
      "agc_mileage_revenue": 0.0,
      "deviation_penalty": 0.0,
      "transmission_fee": 0.0,
      "gov_fund_fee": 0.0,
      "ancillary_fee": 0.44,
      "battery_degradation_cost": 0.0,
      "self_consumption_cost": 0.0,
      "net_revenue": 87.62
    },
    {
      "time": "22:00",
      "soc": 0.8633,
      "net_power_mw": -8.19,
      "lmp": 318.88,
      "energy_revenue": -652.91,
      "agc_capacity_revenue": 82.62,
      "agc_mileage_revenue": 452.17,
      "deviation_penalty": 65.29,
      "transmission_fee": 0.06,
      "gov_fund_fee": 0.04,
      "ancillary_fee": 2.67,
      "battery_degradation_cost": 0.0,
      "self_consumption_cost": 0.0,
      "net_revenue": -186.18
    },
    {
      "time": "22:15",
      "soc": 0.8631,
      "net_power_mw": 0.0,
      "lmp": 307.36,
      "energy_revenue": 0.0,
      "agc_capacity_revenue": 80.02,
      "agc_mileage_revenue": 0.0,
      "deviation_penalty": 0.0,
      "transmission_fee": 0.0,
      "gov_fund_fee": 0.0,
      "ancillary_fee": 0.4,
      "battery_degradation_cost": 0.0,
      "self_consumption_cost": 0.0,
      "net_revenue": 79.62
    },
    {
      "time": "22:30",
      "soc": 0.8776,
      "net_power_mw": -12.85,
      "lmp": 295.13,
      "energy_revenue": -948.11,
      "agc_capacity_revenue": 88.36,
      "agc_mileage_revenue": 709.45,
      "deviation_penalty": 94.81,
      "transmission_fee": 0.1,
      "gov_fund_fee": 0.06,
      "ancillary_fee": 3.99,
      "battery_degradation_cost": 0.0,
      "self_consumption_cost": 0.0,
      "net_revenue": -249.26
    },
    {
      "time": "22:45",
      "soc": 0.8773,
      "net_power_mw": 0.0,
      "lmp": 295.94,
      "energy_revenue": 0.0,
      "agc_capacity_revenue": 74.5,
      "agc_mileage_revenue": 0.0,
      "deviation_penalty": 0.0,
      "transmission_fee": 0.0,
      "gov_fund_fee": 0.0,
      "ancillary_fee": 0.37,
      "battery_degradation_cost": 0.0,
      "self_consumption_cost": 0.0,
      "net_revenue": 74.13
    },
    {
      "time": "23:00",
      "soc": 0.8771,
      "net_power_mw": 0.0,
      "lmp": 292.18,
      "energy_revenue": 0.0,
      "agc_capacity_revenue": 91.89,
      "agc_mileage_revenue": 0.0,
      "deviation_penalty": 0.0,
      "transmission_fee": 0.0,
      "gov_fund_fee": 0.0,
      "ancillary_fee": 0.46,
      "battery_degradation_cost": 0.0,
      "self_consumption_cost": 0.0,
      "net_revenue": 91.43
    },
    {
      "time": "23:15",
      "soc": 0.8768,
      "net_power_mw": 0.0,
      "lmp": 279.73,
      "energy_revenue": 0.0,
      "agc_capacity_revenue": 92.04,
      "agc_mileage_revenue": 0.0,
      "deviation_penalty": 0.0,
      "transmission_fee": 0.0,
      "gov_fund_fee": 0.0,
      "ancillary_fee": 0.46,
      "battery_degradation_cost": 0.0,
      "self_consumption_cost": 0.0,
      "net_revenue": 91.58
    },
    {
      "time": "23:30",
      "soc": 0.8766,
      "net_power_mw": 0.0,
      "lmp": 285.92,
      "energy_revenue": 0.0,
      "agc_capacity_revenue": 82.62,
      "agc_mileage_revenue": 0.0,
      "deviation_penalty": 120.58,
      "transmission_fee": 0.0,
      "gov_fund_fee": 0.0,
      "ancillary_fee": 0.41,
      "battery_degradation_cost": 0.0,
      "self_consumption_cost": 0.0,
      "net_revenue": -38.37
    },
    {
      "time": "23:45",
      "soc": 0.8763,
      "net_power_mw": 0.0,
      "lmp": 285.47,
      "energy_revenue": 0.0,
      "agc_capacity_revenue": 74.04,
      "agc_mileage_revenue": 0.0,
      "deviation_penalty": 0.0,
      "transmission_fee": 0.0,
      "gov_fund_fee": 0.0,
      "ancillary_fee": 0.37,
      "battery_degradation_cost": 0.0,
      "self_consumption_cost": 0.0,
      "net_revenue": 73.67
    }
  ]
}