{
  "date": "2026-06-30",
  "node_name": "节点A",
  "agc_mileage_price": 44.56,
  "intervals": [
    {
      "time": "00:00",
      "lmp_yuan_per_mwh": 275.8,
      "win_charge_mw": 0.0,
      "win_discharge_mw": 0.0,
      "win_agc_capacity_mw": 30.0,
      "agc_capacity_price": 10.27,
      "soc": 0.8414
    },
    {
      "time": "00:15",
      "lmp_yuan_per_mwh": 281.03,
      "win_charge_mw": 0.0,
      "win_discharge_mw": 0.0,
      "win_agc_capacity_mw": 30.0,
      "agc_capacity_price": 9.75,
      "soc": 0.8412
    },
    {
      "time": "00:30",
      "lmp_yuan_per_mwh": 268.44,
      "win_charge_mw": 0.0,
      "win_discharge_mw": 0.0,
      "win_agc_capacity_mw": 30.0,
      "agc_capacity_price": 10.98,
      "soc": 0.8409
    },
    {
      "time": "00:45",
      "lmp_yuan_per_mwh": 263.81,
      "win_charge_mw": 0.0,
      "win_discharge_mw": 0.0,
      "win_agc_capacity_mw": 30.0,
      "agc_capacity_price": 10.07,
      "soc": 0.8407
    },
    {
      "time": "01:00",
      "lmp_yuan_per_mwh": 258.36,
      "win_charge_mw": 0.0,
      "win_discharge_mw": 0.0,
      "win_agc_capacity_mw": 30.0,
      "agc_capacity_price": 11.5,
      "soc": 0.8404
    },
    {
      "time": "01:15",
      "lmp_yuan_per_mwh": 261.33,
      "win_charge_mw": 0.0,
      "win_discharge_mw": 0.0,
      "win_agc_capacity_mw": 30.0,
      "agc_capacity_price": 11.49,
      "soc": 0.8402
    },
    {
      "time": "01:30",
      "lmp_yuan_per_mwh": 259.71,
      "win_charge_mw": 0.0,
      "win_discharge_mw": 0.0,
      "win_agc_capacity_mw": 30.0,
      "agc_capacity_price": 11.97,
      "soc": 0.8399
    },
    {
      "time": "01:45",
      "lmp_yuan_per_mwh": 247.22,
      "win_charge_mw": 0.0,
      "win_discharge_mw": 0.0,
      "win_agc_capacity_mw": 30.0,
      "agc_capacity_price": 11.2,
      "soc": 0.8397
    },
    {
      "time": "02:00",
      "lmp_yuan_per_mwh": 242.11,
      "win_charge_mw": 0.0,
      "win_discharge_mw": 0.0,
      "win_agc_capacity_mw": 30.0,
      "agc_capacity_price": 10.91,
      "soc": 0.8394
    },
    {
      "time": "02:15",
      "lmp_yuan_per_mwh": 238.87,
      "win_charge_mw": 0.0,
      "win_discharge_mw": 0.0,
      "win_agc_capacity_mw": 30.0,
      "agc_capacity_price": 10.87,
      "soc": 0.8392
    },
    {
      "time": "02:30",
      "lmp_yuan_per_mwh": 234.09,
      "win_charge_mw": 0.0,
      "win_discharge_mw": 0.0,
      "win_agc_capacity_mw": 30.0,
      "agc_capacity_price": 10.23,
      "soc": 0.8389
    },
    {
      "time": "02:45",
      "lmp_yuan_per_mwh": 238.0,
      "win_charge_mw": 0.0,
      "win_discharge_mw": 0.0,
      "win_agc_capacity_mw": 30.0,
      "agc_capacity_price": 12.21,
      "soc": 0.8387
    },
    {
      "time": "03:00",
      "lmp_yuan_per_mwh": 233.02,
      "win_charge_mw": 0.0,
      "win_discharge_mw": 0.0,
      "win_agc_capacity_mw": 30.0,
      "agc_capacity_price": 11.25,
      "soc": 0.8384
    },
    {
      "time": "03:15",
      "lmp_yuan_per_mwh": 242.73,
      "win_charge_mw": 0.0,
      "win_discharge_mw": 0.0,
      "win_agc_capacity_mw": 30.0,
      "agc_capacity_price": 11.31,
      "soc": 0.8382
    },
    {
      "time": "03:30",
      "lmp_yuan_per_mwh": 237.23,
      "win_charge_mw": 0.0,
      "win_discharge_mw": 0.0,
      "win_agc_capacity_mw": 30.0,
      "agc_capacity_price": 11.88,
      "soc": 0.8379
    },
    {
      "time": "03:45",
      "lmp_yuan_per_mwh": 248.58,
      "win_charge_mw": 0.0,
      "win_discharge_mw": 0.0,
      "win_agc_capacity_mw": 30.0,
      "agc_capacity_price": 10.9,
      "soc": 0.8377
    },
    {
      "time": "04:00",
      "lmp_yuan_per_mwh": 249.18,
      "win_charge_mw": 0.0,
      "win_discharge_mw": 0.0,
      "win_agc_capacity_mw": 30.0,
      "agc_capacity_price": 12.01,
      "soc": 0.8374
    },
    {
      "time": "04:15",
      "lmp_yuan_per_mwh": 251.66,
      "win_charge_mw": 0.0,
      "win_discharge_mw": 0.0,
      "win_agc_capacity_mw": 30.0,
      "agc_capacity_price": 11.53,
      "soc": 0.8372
    },
    {
      "time": "04:30",
      "lmp_yuan_per_mwh": 255.53,
      "win_charge_mw": 0.0,
      "win_discharge_mw": 0.0,
      "win_agc_capacity_mw": 30.0,
      "agc_capacity_price": 11.32,
      "soc": 0.8369
    },
    {
      "time": "04:45",
      "lmp_yuan_per_mwh": 257.81,
      "win_charge_mw": 0.0,
      "win_discharge_mw": 0.0,
      "win_agc_capacity_mw": 30.0,
      "agc_capacity_price": 11.64,
      "soc": 0.8367
    },
    {
      "time": "05:00",
      "lmp_yuan_per_mwh": 262.84,
      "win_charge_mw": 0.0,
      "win_discharge_mw": 0.0,
      "win_agc_capacity_mw": 30.0,
      "agc_capacity_price": 11.68,
      "soc": 0.8364
    },
    {
      "time": "05:15",
      "lmp_yuan_per_mwh": 271.96,
      "win_charge_mw": 0.0,
      "win_discharge_mw": 0.0,
      "win_agc_capacity_mw": 30.0,
      "agc_capacity_price": 10.68,
      "soc": 0.8362
    },
    {
      "time": "05:30",
      "lmp_yuan_per_mwh": 289.43,
      "win_charge_mw": 0.0,
      "win_discharge_mw": 0.0,
      "win_agc_capacity_mw": 30.0,
      "agc_capacity_price": 11.62,
      "soc": 0.8359
    },
    {
      "time": "05:45",
      "lmp_yuan_per_mwh": 303.1,
      "win_charge_mw": 0.0,
      "win_discharge_mw": 0.0,
      "win_agc_capacity_mw": 30.0,
      "agc_capacity_price": 11.5,
      "soc": 0.8357
    },
    {
      "time": "06:00",
      "lmp_yuan_per_mwh": 311.9,
      "win_charge_mw": 0.0,
      "win_discharge_mw": 0.0,
      "win_agc_capacity_mw": 30.0,
      "agc_capacity_price": 12.3,
      "soc": 0.8354
    },
    {
      "time": "06:15",
      "lmp_yuan_per_mwh": 336.55,
      "win_charge_mw": 0.0,
      "win_discharge_mw": 0.0,
      "win_agc_capacity_mw": 30.0,
      "agc_capacity_price": 12.34,
      "soc": 0.8352
    },
    {
      "time": "06:30",
      "lmp_yuan_per_mwh": 352.81,
      "win_charge_mw": 0.0,
      "win_discharge_mw": 0.0,
      "win_agc_capacity_mw": 30.0,
      "agc_capacity_price": 11.7,
      "soc": 0.8349
    },
    {
      "time": "06:45",
      "lmp_yuan_per_mwh": 366.59,
      "win_charge_mw": 0.0,
      "win_discharge_mw": 0.0,
      "win_agc_capacity_mw": 30.0,
      "agc_capacity_price": 11.86,
      "soc": 0.8347
    },
    {
      "time": "07:00",
      "lmp_yuan_per_mwh": 389.18,
      "win_charge_mw": 0.0,
      "win_discharge_mw": 0.0,
      "win_agc_capacity_mw": 30.0,
      "agc_capacity_price": 12.91,
      "soc": 0.8344
    },
    {
      "time": "07:15",
      "lmp_yuan_per_mwh": 409.8,
      "win_charge_mw": 0.0,
      "win_discharge_mw": 0.0,
      "win_agc_capacity_mw": 30.0,
      "agc_capacity_price": 12.39,
      "soc": 0.8342
    },
    {
      "time": "07:30",
      "lmp_yuan_per_mwh": 438.71,
      "win_charge_mw": 0.0,
      "win_discharge_mw": 0.0,
      "win_agc_capacity_mw": 30.0,
      "agc_capacity_price": 12.37,
      "soc": 0.8339
    },
    {
      "time": "07:45",
      "lmp_yuan_per_mwh": 447.71,
      "win_charge_mw": 0.0,
      "win_discharge_mw": 0.0,
      "win_agc_capacity_mw": 30.0,
      "agc_capacity_price": 13.17,
      "soc": 0.8337
    },
    {
      "time": "08:00",
      "lmp_yuan_per_mwh": 461.19,
      "win_charge_mw": 0.0,
      "win_discharge_mw": 0.0,
      "win_agc_capacity_mw": 30.0,
      "agc_capacity_price": 14.32,
      "soc": 0.8334
    },
    {
      "time": "08:15",
      "lmp_yuan_per_mwh": 477.97,
      "win_charge_mw": 0.0,
      "win_discharge_mw": 0.0,
      "win_agc_capacity_mw": 30.0,
      "agc_capacity_price": 12.38,
      "soc": 0.8332
    },
    {
      "time": "08:30",
      "lmp_yuan_per_mwh": 483.31,
      "win_charge_mw": 0.0,
      "win_discharge_mw": 0.0,
      "win_agc_capacity_mw": 30.0,
      "agc_capacity_price": 14.01,
      "soc": 0.8329
    },
    {
      "time": "08:45",
      "lmp_yuan_per_mwh": 470.2,
      "win_charge_mw": 0.0,
      "win_discharge_mw": 0.0,
      "win_agc_capacity_mw": 30.0,
      "agc_capacity_price": 11.88,
      "soc": 0.8327
    },
    {
      "time": "09:00",
      "lmp_yuan_per_mwh": 474.8,
      "win_charge_mw": 0.0,
      "win_discharge_mw": 0.0,
      "win_agc_capacity_mw": 30.0,
      "agc_capacity_price": 12.32,
      "soc": 0.8324
    },
    {
      "time": "09:15",
      "lmp_yuan_per_mwh": 451.41,
      "win_charge_mw": 0.0,
      "win_discharge_mw": 0.0,
      "win_agc_capacity_mw": 30.0,
      "agc_capacity_price": 13.96,
      "soc": 0.8322
    },
    {
      "time": "09:30",
      "lmp_yuan_per_mwh": 441.2,
      "win_charge_mw": 0.0,
      "win_discharge_mw": 0.0,
      "win_agc_capacity_mw": 30.0,
      "agc_capacity_price": 12.14,
      "soc": 0.8319
    },
    {
      "time": "09:45",
      "lmp_yuan_per_mwh": 425.76,
      "win_charge_mw": 0.0,
      "win_discharge_mw": 0.0,
      "win_agc_capacity_mw": 30.0,
      "agc_capacity_price": 12.39,
      "soc": 0.8317
    },
    {
      "time": "10:00",
      "lmp_yuan_per_mwh": 405.65,
      "win_charge_mw": 0.0,
      "win_discharge_mw": 0.0,
      "win_agc_capacity_mw": 30.0,
      "agc_capacity_price": 11.26,
      "soc": 0.8314
    },
    {
      "time": "10:15",
      "lmp_yuan_per_mwh": 387.16,
      "win_charge_mw": 0.0,
      "win_discharge_mw": 0.0,
      "win_agc_capacity_mw": 30.0,
      "agc_capacity_price": 11.1,
      "soc": 0.8312
    },
    {
      "time": "10:30",
      "lmp_yuan_per_mwh": 351.51,
      "win_charge_mw": 0.0,
      "win_discharge_mw": 0.0,
      "win_agc_capacity_mw": 30.0,
      "agc_capacity_price": 11.21,
      "soc": 0.8309
    },
    {
      "time": "10:45",
      "lmp_yuan_per_mwh": 337.2,
      "win_charge_mw": 0.0,
      "win_discharge_mw": 0.0,
      "win_agc_capacity_mw": 30.0,
      "agc_capacity_price": 11.82,
      "soc": 0.8307
    },
    {
      "time": "11:00",
      "lmp_yuan_per_mwh": 327.99,
      "win_charge_mw": 0.0,
      "win_discharge_mw": 0.0,
      "win_agc_capacity_mw": 30.0,
      "agc_capacity_price": 9.58,
      "soc": 0.8304
    },
    {
      "time": "11:15",
      "lmp_yuan_per_mwh": 312.82,
      "win_charge_mw": 0.0,
      "win_discharge_mw": 0.0,
      "win_agc_capacity_mw": 30.0,
      "agc_capacity_price": 12.07,
      "soc": 0.8302
    },
    {
      "time": "11:30",
      "lmp_yuan_per_mwh": 299.09,
      "win_charge_mw": 0.0,
      "win_discharge_mw": 0.0,
      "win_agc_capacity_mw": 30.0,
      "agc_capacity_price": 11.09,
      "soc": 0.8299
    },
    {
      "time": "11:45",
      "lmp_yuan_per_mwh": 279.48,
      "win_charge_mw": 0.0,
      "win_discharge_mw": 0.0,
      "win_agc_capacity_mw": 30.0,
      "agc_capacity_price": 9.64,
      "soc": 0.8297
    },
    {
      "time": "12:00",
      "lmp_yuan_per_mwh": 268.25,
      "win_charge_mw": 0.0,
      "win_discharge_mw": 0.0,
      "win_agc_capacity_mw": 30.0,
      "agc_capacity_price": 11.15,
      "soc": 0.8294
    },
    {
      "time": "12:15",
      "lmp_yuan_per_mwh": 274.27,
      "win_charge_mw": 0.0,
      "win_discharge_mw": 0.0,
      "win_agc_capacity_mw": 30.0,
      "agc_capacity_price": 12.29,
      "soc": 0.8292
    },
    {
      "time": "12:30",
      "lmp_yuan_per_mwh": 269.84,
      "win_charge_mw": 0.0,
      "win_discharge_mw": 0.0,
      "win_agc_capacity_mw": 30.0,
      "agc_capacity_price": 12.33,
      "soc": 0.8289
    },
    {
      "time": "12:45",
      "lmp_yuan_per_mwh": 257.66,
      "win_charge_mw": 0.0,
      "win_discharge_mw": 0.0,
      "win_agc_capacity_mw": 30.0,
      "agc_capacity_price": 11.14,
      "soc": 0.8287
    },
    {
      "time": "13:00",
      "lmp_yuan_per_mwh": 261.48,
      "win_charge_mw": 0.0,
      "win_discharge_mw": 0.0,
      "win_agc_capacity_mw": 30.0,
      "agc_capacity_price": 11.67,
      "soc": 0.8284
    },
    {
      "time": "13:15",
      "lmp_yuan_per_mwh": 277.61,
      "win_charge_mw": 0.0,
      "win_discharge_mw": 0.0,
      "win_agc_capacity_mw": 30.0,
      "agc_capacity_price": 11.54,
      "soc": 0.8282
    },
    {
      "time": "13:30",
      "lmp_yuan_per_mwh": 281.69,
      "win_charge_mw": 0.0,
      "win_discharge_mw": 0.0,
      "win_agc_capacity_mw": 30.0,
      "agc_capacity_price": 12.09,
      "soc": 0.8279
    },
    {
      "time": "13:45",
      "lmp_yuan_per_mwh": 279.12,
      "win_charge_mw": 0.0,
      "win_discharge_mw": 0.0,
      "win_agc_capacity_mw": 30.0,
      "agc_capacity_price": 10.54,
      "soc": 0.8277
    },
    {
      "time": "14:00",
      "lmp_yuan_per_mwh": 293.78,
      "win_charge_mw": 0.0,
      "win_discharge_mw": 0.0,
      "win_agc_capacity_mw": 30.0,
      "agc_capacity_price": 11.15,
      "soc": 0.8274
    },
    {
      "time": "14:15",
      "lmp_yuan_per_mwh": 298.05,
      "win_charge_mw": 0.0,
      "win_discharge_mw": 0.0,
      "win_agc_capacity_mw": 30.0,
      "agc_capacity_price": 11.36,
      "soc": 0.8272
    },
    {
      "time": "14:30",
      "lmp_yuan_per_mwh": 296.46,
      "win_charge_mw": 0.0,
      "win_discharge_mw": 0.0,
      "win_agc_capacity_mw": 30.0,
      "agc_capacity_price": 10.06,
      "soc": 0.8269
    },
    {
      "time": "14:45",
      "lmp_yuan_per_mwh": 302.57,
      "win_charge_mw": 0.0,
      "win_discharge_mw": 0.0,
      "win_agc_capacity_mw": 30.0,
      "agc_capacity_price": 11.74,
      "soc": 0.8267
    },
    {
      "time": "15:00",
      "lmp_yuan_per_mwh": 314.47,
      "win_charge_mw": 0.0,
      "win_discharge_mw": 0.0,
      "win_agc_capacity_mw": 30.0,
      "agc_capacity_price": 9.9,
      "soc": 0.8264
    },
    {
      "time": "15:15",
      "lmp_yuan_per_mwh": 328.99,
      "win_charge_mw": 0.0,
      "win_discharge_mw": 0.0,
      "win_agc_capacity_mw": 30.0,
      "agc_capacity_price": 12.34,
      "soc": 0.8262
    },
    {
      "time": "15:30",
      "lmp_yuan_per_mwh": 334.38,
      "win_charge_mw": 0.0,
      "win_discharge_mw": 0.0,
      "win_agc_capacity_mw": 30.0,
      "agc_capacity_price": 9.94,
      "soc": 0.8259
    },
    {
      "time": "15:45",
      "lmp_yuan_per_mwh": 343.33,
      "win_charge_mw": 0.0,
      "win_discharge_mw": 0.0,
      "win_agc_capacity_mw": 30.0,
      "agc_capacity_price": 10.68,
      "soc": 0.8257
    },
    {
      "time": "16:00",
      "lmp_yuan_per_mwh": 344.18,
      "win_charge_mw": 0.0,
      "win_discharge_mw": 0.0,
      "win_agc_capacity_mw": 30.0,
      "agc_capacity_price": 12.34,
      "soc": 0.8254
    },
    {
      "time": "16:15",
      "lmp_yuan_per_mwh": 367.26,
      "win_charge_mw": 0.0,
      "win_discharge_mw": 0.0,
      "win_agc_capacity_mw": 30.0,
      "agc_capacity_price": 14.15,
      "soc": 0.8252
    },
    {
      "time": "16:30",
      "lmp_yuan_per_mwh": 375.68,
      "win_charge_mw": 0.0,
      "win_discharge_mw": 0.0,
      "win_agc_capacity_mw": 30.0,
      "agc_capacity_price": 11.72,
      "soc": 0.8249
    },
    {
      "time": "16:45",
      "lmp_yuan_per_mwh": 394.27,
      "win_charge_mw": 0.0,
      "win_discharge_mw": 0.0,
      "win_agc_capacity_mw": 30.0,
      "agc_capacity_price": 13.51,
      "soc": 0.8247
    },
    {
      "time": "17:00",
      "lmp_yuan_per_mwh": 409.83,
      "win_charge_mw": 0.0,
      "win_discharge_mw": 0.0,
      "win_agc_capacity_mw": 30.0,
      "agc_capacity_price": 13.93,
      "soc": 0.8244
    },
    {
      "time": "17:15",
      "lmp_yuan_per_mwh": 434.04,
      "win_charge_mw": 0.0,
      "win_discharge_mw": 0.0,
      "win_agc_capacity_mw": 30.0,
      "agc_capacity_price": 12.96,
      "soc": 0.8242
    },
    {
      "time": "17:30",
      "lmp_yuan_per_mwh": 459.19,
      "win_charge_mw": 0.0,
      "win_discharge_mw": 0.0,
      "win_agc_capacity_mw": 30.0,
      "agc_capacity_price": 12.55,
      "soc": 0.8239
    },
    {
      "time": "17:45",
      "lmp_yuan_per_mwh": 467.34,
      "win_charge_mw": 0.0,
      "win_discharge_mw": 0.0,
      "win_agc_capacity_mw": 30.0,
      "agc_capacity_price": 11.47,
      "soc": 0.8237
    },
    {
      "time": "18:00",
      "lmp_yuan_per_mwh": 488.0,
      "win_charge_mw": 0.0,
      "win_discharge_mw": 0.0,
      "win_agc_capacity_mw": 30.0,
      "agc_capacity_price": 12.26,
      "soc": 0.8234
    },
    {
      "time": "18:15",
      "lmp_yuan_per_mwh": 493.31,
      "win_charge_mw": 0.0,
      "win_discharge_mw": 0.0,
      "win_agc_capacity_mw": 30.0,
      "agc_capacity_price": 13.52,
      "soc": 0.8232
    },
    {
      "time": "18:30",
      "lmp_yuan_per_mwh": 503.38,
      "win_charge_mw": 0.0,
      "win_discharge_mw": 0.0,
      "win_agc_capacity_mw": 30.0,
      "agc_capacity_price": 11.86,
      "soc": 0.8229
    },
    {
      "time": "18:45",
      "lmp_yuan_per_mwh": 521.05,
      "win_charge_mw": 0.0,
      "win_discharge_mw": 7.36,
      "win_agc_capacity_mw": 30.0,
      "agc_capacity_price": 12.07,
      "soc": 0.8227
    },
    {
      "time": "19:00",
      "lmp_yuan_per_mwh": 516.75,
      "win_charge_mw": 0.0,
      "win_discharge_mw": 0.0,
      "win_agc_capacity_mw": 30.0,
      "agc_capacity_price": 12.76,
      "soc": 0.8124
    },
    {
      "time": "19:15",
      "lmp_yuan_per_mwh": 517.7,
      "win_charge_mw": 0.0,
      "win_discharge_mw": 0.0,
      "win_agc_capacity_mw": 30.0,
      "agc_capacity_price": 14.12,
      "soc": 0.8122
    },
    {
      "time": "19:30",
      "lmp_yuan_per_mwh": 515.15,
      "win_charge_mw": 0.0,
      "win_discharge_mw": 0.0,
      "win_agc_capacity_mw": 30.0,
      "agc_capacity_price": 11.53,
      "soc": 0.8119
    },
    {
      "time": "19:45",
      "lmp_yuan_per_mwh": 496.17,
      "win_charge_mw": 0.0,
      "win_discharge_mw": 0.0,
      "win_agc_capacity_mw": 30.0,
      "agc_capacity_price": 14.06,
      "soc": 0.8117
    },
    {
      "time": "20:00",
      "lmp_yuan_per_mwh": 486.66,
      "win_charge_mw": 0.0,
      "win_discharge_mw": 0.0,
      "win_agc_capacity_mw": 30.0,
      "agc_capacity_price": 12.19,
      "soc": 0.8114
    },
    {
      "time": "20:15",
      "lmp_yuan_per_mwh": 477.81,
      "win_charge_mw": 0.0,
      "win_discharge_mw": 0.0,
      "win_agc_capacity_mw": 30.0,
      "agc_capacity_price": 12.37,
      "soc": 0.8112
    },
    {
      "time": "20:30",
      "lmp_yuan_per_mwh": 447.35,
      "win_charge_mw": 0.0,
      "win_discharge_mw": 0.0,
      "win_agc_capacity_mw": 30.0,
      "agc_capacity_price": 13.35,
      "soc": 0.8109
    },
    {
      "time": "20:45",
      "lmp_yuan_per_mwh": 437.67,
      "win_charge_mw": 0.0,
      "win_discharge_mw": 0.0,
      "win_agc_capacity_mw": 30.0,
      "agc_capacity_price": 12.14,
      "soc": 0.8107
    },
    {
      "time": "21:00",
      "lmp_yuan_per_mwh": 415.41,
      "win_charge_mw": 0.0,
      "win_discharge_mw": 0.0,
      "win_agc_capacity_mw": 30.0,
      "agc_capacity_price": 11.38,
      "soc": 0.8104
    },
    {
      "time": "21:15",
      "lmp_yuan_per_mwh": 401.94,
      "win_charge_mw": 0.0,
      "win_discharge_mw": 0.0,
      "win_agc_capacity_mw": 30.0,
      "agc_capacity_price": 10.06,
      "soc": 0.8102
    },
    {
      "time": "21:30",
      "lmp_yuan_per_mwh": 375.53,
      "win_charge_mw": 0.0,
      "win_discharge_mw": 0.0,
      "win_agc_capacity_mw": 30.0,
      "agc_capacity_price": 9.61,
      "soc": 0.8099
    },
    {
      "time": "21:45",
      "lmp_yuan_per_mwh": 358.59,
      "win_charge_mw": 0.0,
      "win_discharge_mw": 0.0,
      "win_agc_capacity_mw": 30.0,
      "agc_capacity_price": 11.76,
      "soc": 0.8097
    },
    {
      "time": "22:00",
      "lmp_yuan_per_mwh": 355.73,
      "win_charge_mw": 0.0,
      "win_discharge_mw": 0.0,
      "win_agc_capacity_mw": 30.0,
      "agc_capacity_price": 11.58,
      "soc": 0.8094
    },
    {
      "time": "22:15",
      "lmp_yuan_per_mwh": 338.32,
      "win_charge_mw": 0.0,
      "win_discharge_mw": 0.0,
      "win_agc_capacity_mw": 30.0,
      "agc_capacity_price": 9.72,
      "soc": 0.8092
    },
    {
      "time": "22:30",
      "lmp_yuan_per_mwh": 327.01,
      "win_charge_mw": 0.0,
      "win_discharge_mw": 0.0,
      "win_agc_capacity_mw": 30.0,
      "agc_capacity_price": 11.49,
      "soc": 0.8089
    },
    {
      "time": "22:45",
      "lmp_yuan_per_mwh": 316.17,
      "win_charge_mw": 0.0,
      "win_discharge_mw": 0.0,
      "win_agc_capacity_mw": 30.0,
      "agc_capacity_price": 11.92,
      "soc": 0.8087
    },
    {
      "time": "23:00",
      "lmp_yuan_per_mwh": 324.59,
      "win_charge_mw": 0.0,
      "win_discharge_mw": 0.0,
      "win_agc_capacity_mw": 30.0,
      "agc_capacity_price": 9.6,
      "soc": 0.8084
    },
    {
      "time": "23:15",
      "lmp_yuan_per_mwh": 305.37,
      "win_charge_mw": 0.0,
      "win_discharge_mw": 0.0,
      "win_agc_capacity_mw": 30.0,
      "agc_capacity_price": 9.71,
      "soc": 0.8082
    },
    {
      "time": "23:30",
      "lmp_yuan_per_mwh": 304.95,
      "win_charge_mw": 0.0,
      "win_discharge_mw": 0.0,
      "win_agc_capacity_mw": 30.0,
      "agc_capacity_price": 9.48,
      "soc": 0.8079
    },
    {
      "time": "23:45",
      "lmp_yuan_per_mwh": 301.16,
      "win_charge_mw": 0.0,
      "win_discharge_mw": 0.0,
      "win_agc_capacity_mw": 30.0,
      "agc_capacity_price": 11.25,
      "soc": 0.8077
    }
  ]
}